pyopenhardwaremonitor/__init__.py
pyopenhardwaremonitor/api.py
pyopenhardwaremonitor/const.py
pyopenhardwaremonitor/exceptions.py
pyopenhardwaremonitor/types.py
pyopenhardwaremonitor-0.2.5.dist-info/LICENSE.md
pyopenhardwaremonitor-0.2.5.dist-info/METADATA
pyopenhardwaremonitor-0.2.5.dist-info/WHEEL
pyopenhardwaremonitor-0.2.5.dist-info/top_level.txt
pyopenhardwaremonitor-0.2.5.dist-info/RECORD
